app.py
run_app.py
EasyPipUpload-0.1.data/scripts/run_app.py
EasyPipUpload-0.1.dist-info/LICENSE.txt
EasyPipUpload-0.1.dist-info/METADATA
EasyPipUpload-0.1.dist-info/WHEEL
EasyPipUpload-0.1.dist-info/top_level.txt
EasyPipUpload-0.1.dist-info/RECORD
