Metadata-Version: 2.1
Name: EasyPipUpload
Version: 0.1
Summary: Effortlessly uploading your Python scripts to the Python Package Index (PyPI). No more command-line struggles!
Home-page: https://github.com/CodingSangh
Author: CodingSangh
Classifier: License :: OSI Approved :: MIT License
Classifier: Programming Language :: Python :: 3
License-File: LICENSE.txt
Requires-Dist: flask
Requires-Dist: waitress
